README.md
setup.py
BMPboot/__init__.py
BMPboot/address_book.py
BMPboot/main.py
BMPboot.egg-info/PKG-INFO
BMPboot.egg-info/SOURCES.txt
BMPboot.egg-info/dependency_links.txt
BMPboot.egg-info/entry_points.txt
BMPboot.egg-info/requires.txt
BMPboot.egg-info/top_level.txt
test/testowanie.py