Metadata-Version: 2.1
Name: BMPboot
Version: 3.5
Summary: The Best of Boots: "BMP" - an address book application
Author: Bartosz, Michał, Piotr
Author-email: it@bartoszzygmunt.pl
Requires-Dist: thefuzz
